{
    "data": [
        {
            "id": 1,
            "url": "/assets/productos/zapatilla_1.jpg",
            "title": "Zapatilla 1-XFK",
            "price": 100,
            "category": "Zapatilla",
            "sizes": ["41"],
            "colors": ["Rojo"]
        },
        {
            "id": 2,
            "url": "/assets/productos/zapatilla_2.jpg",
            "title": "Zapatilla 2000-X",
            "price": 100,
            "category": "Zapatilla",
             "sizes": ["40"],
            "colors": ["Azul"]
        },
        {
            "id": 3,
            "url": "/assets/productos/zapatilla_3.jpg",
            "title": "Zapatilla 3 Run",
            "price": 100,
            "category": "Zapato",
            "sizes": ["40","41"],
            "colors": ["Azul"]
        },
        {
            "id": 4,
            "url": "/assets/productos/zapatilla_3.jpg",
            "title": "Zapatilla 3 Run",
            "price": 100,
            "category": "Zapato",
            "sizes": ["40","41"],
            "colors": ["Verde"]
        },
         {
            "id": 5,
            "url": "/assets/productos/zapatilla_2.jpg",
            "title": "Zapatilla 2000-X",
            "price": 100,
            "category": "Sandalia",
            "sizes": ["39"],
            "colors": ["Rojo"]
        },
          {
            "id": 6,
            "url": "/assets/productos/zapatilla_1.jpg",
            "title": "Zapatilla 1-XFK",
            "price": 100,
            "category": "Sandalia",
            "sizes": ["23"],
            "colors": ["Negro"]
        },
        {
            "id": 7,
            "url": "/assets/productos/zapatilla_1.jpg",
            "title": "Zapatilla 1-XFK",
            "price": 100,
            "category": "Zapatilla",
            "sizes": ["41"],
            "colors": ["Rojo"]
        },
        {
            "id": 8,
            "url": "/assets/productos/zapatilla_2.jpg",
            "title": "Zapatilla 2000-X",
            "price": 100,
            "category": "Zapato",
            "sizes": ["42"],
            "colors": ["Rojo"]

        },
        {
            "id": 9,
            "url": "/assets/productos/zapatilla_3.jpg",
            "title": "Zapatilla 3 Run",
            "price": 100,
            "category": "Zapato",
            "sizes": ["39","40","41","42", "44"], 
            "colors": ["Rojo", "Azul", "Verde"]
        }
    ],
    "options": {
        "categories":{
            "name": "Categorias",
            "options": ["Zapatilla", "Zapato", "Sandalia"]
        },
        "sizes": {
            "name": "Talle",
            "options": ["39", "40", "41", "42", "44"]
        },
        "colors": {
            "name": "Colores",
            "options":["Rojo", "Azul", "Verde", "Negro", "Blanco"]
        }
    } 
}